pokecuilmas/__init__.py
pokecuilmas/pokemon.csv
pokecuilmas/random_pokemon.py
pokecuilmas-1.0.0.dist-info/METADATA
pokecuilmas-1.0.0.dist-info/WHEEL
pokecuilmas-1.0.0.dist-info/top_level.txt
pokecuilmas-1.0.0.dist-info/RECORD
