Metadata-Version: 2.1
Name: pokecuilmas
Version: 1.0.0
Summary: Libreria para generar un pokemon aleatorio
Author: Daniel Rayon
Author-email: 202224029_beltran@tesch.edu.mx
Requires-Dist: pandas
